{
  "Terrains": [
    {
      "Name": "Grass",
      "Image": {
        "TileSetPath": "Tilesets/UnderWorld.tileset.json",
        "x": 21,
        "y": 5
      },
      "Color": {
        "Color": "#FF1BA32D"
      },
      "Floor": {
        "Opacity": 80
      },
      "Wall": {
        "Opacity": 50
      }
    },
    {
      "Name": "Water",
      "Image": {
        "TileSetPath": "Tilesets/UnderWorld.tileset.json",
        "x": 9,
        "y": 14
      },
      "Color": {
        "Color": "#FF20679C"
      },
      "Floor": {
        "Opacity": 25
      }
    }
  ]
}